{
  "name": "Hello World",
  "icon": "👋",
  "description": "A minimal Hello World workflow. When run, it executes a script that logs Hello, World! — a great starting point for understanding how Automa works.",
  "version": "1.28.4",
  "globalData": "",
  "table": [],
  "settings": {
    "publicId": "",
    "blockDelay": 0,
    "saveLog": true,
    "debugMode": false,
    "restartTimes": 3,
    "notification": true,
    "execContext": "popup",
    "reuseLastState": false,
    "inputAutocomplete": true,
    "onError": "stop-workflow",
    "executedBlockOnWeb": false,
    "insertDefaultColumn": false,
    "defaultColumnName": "column"
  },
  "drawflow": {
    "edges": [
      {
        "id": "vueflow__edge-trigger-1trigger-1-output-1-javascript-1javascript-1-input-1",
        "source": "trigger-1",
        "target": "javascript-1",
        "sourceHandle": "trigger-1-output-1",
        "targetHandle": "javascript-1-input-1",
        "type": "custom",
        "updatable": true,
        "selectable": true,
        "markerEnd": "arrowclosed",
        "data": {},
        "events": {}
      }
    ],
    "nodes": [
      {
        "id": "trigger-1",
        "label": "trigger",
        "type": "BlockBasic",
        "position": { "x": 96, "y": 200 },
        "computedPosition": { "x": 96, "y": 200, "z": 0 },
        "dimensions": { "width": 192, "height": 72 },
        "handleBounds": {
          "source": [
            {
              "id": "trigger-1-output-1",
              "position": "right",
              "x": 196,
              "y": 28,
              "width": 16,
              "height": 16
            }
          ]
        },
        "selected": false,
        "dragging": false,
        "resizing": false,
        "initialized": true,
        "events": {},
        "data": {
          "disableBlock": false,
          "description": "",
          "type": "manual",
          "interval": 60,
          "delay": 5,
          "date": "",
          "time": "00:00",
          "url": "",
          "shortcut": "",
          "activeInInput": false,
          "isUrlRegex": false,
          "days": [],
          "contextMenuName": "",
          "contextTypes": [],
          "parameters": [],
          "preferParamsInTab": false,
          "observeElement": {
            "selector": "",
            "baseSelector": "",
            "matchPattern": "",
            "targetOptions": {
              "subtree": false,
              "childList": true,
              "attributes": false,
              "attributeFilter": [],
              "characterData": false
            },
            "baseElOptions": {
              "subtree": false,
              "childList": true,
              "attributes": false,
              "attributeFilter": [],
              "characterData": false
            }
          }
        }
      },
      {
        "id": "javascript-1",
        "label": "javascript",
        "type": "BlockBasic",
        "position": { "x": 388, "y": 200 },
        "computedPosition": { "x": 388, "y": 200, "z": 0 },
        "dimensions": { "width": 192, "height": 72 },
        "handleBounds": {
          "source": [
            {
              "id": "javascript-1-output-1",
              "position": "right",
              "x": 196,
              "y": 28,
              "width": 16,
              "height": 16
            }
          ],
          "target": [
            {
              "id": "javascript-1-input-1",
              "position": "left",
              "x": -20,
              "y": 28,
              "width": 16,
              "height": 16
            }
          ]
        },
        "selected": false,
        "dragging": false,
        "resizing": false,
        "initialized": true,
        "events": {},
        "data": {
          "disableBlock": false,
          "description": "",
          "code": "automaLog('Hello, World!');\nreturn 'Hello, World!';",
          "everyNewTab": false
        }
      }
    ],
    "zoom": 1
  }
}
